latex_table_generator_homework_itmo_liskunovich-0.3.1.dist-info/licenses/LICENSE
table_generator/__init__.py
table_generator/table_gen.py
latex_table_generator_homework_itmo_liskunovich-0.3.1.dist-info/METADATA
latex_table_generator_homework_itmo_liskunovich-0.3.1.dist-info/WHEEL
latex_table_generator_homework_itmo_liskunovich-0.3.1.dist-info/top_level.txt
latex_table_generator_homework_itmo_liskunovich-0.3.1.dist-info/RECORD
