Metadata-Version: 2.4
Name: latex_table_generator_homework_itmo_liskunovich
Version: 0.3.1
Summary: Simple library to generate LaTeX code for tables and figures
Author: David Liskunovich
Author-email: devid02ru@gmail.com
Classifier: Programming Language :: Python :: 3
Classifier: License :: OSI Approved :: MIT License
Requires-Python: >=3.7
License-File: LICENSE
Dynamic: author
Dynamic: author-email
Dynamic: classifier
Dynamic: license-file
Dynamic: requires-python
Dynamic: summary
